{"name":"collections/blog/posts/c82e229c9416","__resolveType":"blog/loaders/Blogpost.ts","post":{"authors":[],"categories":[],"title":"Loader","excerpt":"A loader is a function or component that fetches and prepares data before it is rendered on a web page. Loaders ensure that the necessary data is available and formatted correctly.","date":"2024-08-14","slug":"loader","content":"<p>In web development, especially within CMS and headless CMS environments, loaders are essential for managing data flow, ensuring that the right data is fetched and prepared before a page is rendered. This process optimizes performance and enhances user experience by delivering dynamic and data-driven content efficiently.</p><p></p><h1>What is a loader?</h1><p>A loader is a function or component responsible for fetching and preparing data required for rendering a web page or application. In CMS and headless CMS contexts, loaders manage data flow from various sources, including APIs, databases, and third-party services. They ensure that the necessary data is available and correctly formatted before it is passed to the frontend for display.</p><p></p><h1>How do loaders work in CMS and headless CMS?</h1><p>In CMS and headless CMS environments, loaders are integral to delivering dynamic, data-driven content. Here’s how loaders function within these contexts:</p><p></p><h2>Data fetching and preparation</h2><p>Loaders are responsible for fetching data from various sources, transforming it as needed, and preparing it for use by the frontend components. For example, in a headless CMS such as Strapi, a loader can fetch product data from an ecommerce API, transform it into a format compatible with the frontend, and pass it to a React component for rendering.</p><h2>Integration with APIs</h2><p>Loaders integrate with APIs to fetch external data, ensuring that the content displayed on the website is up-to-date and relevant. For example, a news website using a headless CMS can implement loaders to fetch the latest articles from an external news API, ensuring that the homepage always displays current news.</p><h2>Data transformation and validation</h2><p>Loaders often include logic to transform and validate data, ensuring it meets the requirements of the application. For example, a loader in a traditional CMS like WordPress can fetch user-generated content, sanitize it to prevent security vulnerabilities and format it for display in a custom theme.</p><p></p><p></p><h1>Examples of loaders in action</h1><h2>Ecommerce product loader</h2><ul><li><p><strong>Scenario:</strong> An online store needs to display a list of products dynamically on the homepage.</p></li><li><p><strong>Implementation:</strong> A loader fetches product data from an ecommerce API, formats it into a structure suitable for the frontend, and passes it to a component that renders the product list.</p></li><li><p><strong>Result:</strong> The homepage dynamically displays the latest products, providing users with up-to-date information and enhancing their shopping experience.</p></li></ul><h2>Blog post loader</h2><ul><li><p><strong>Scenario:</strong> A blog wants to feature the latest posts on its homepage.</p></li><li><p><strong>Implementation:</strong> A loader retrieves the latest blog posts from the CMS, formats the data, and provides it to the frontend component responsible for displaying the post previews.</p></li><li><p><strong>Result:</strong> The blog's homepage always showcases the most recent content, attracting readers and increasing engagement.</p></li></ul><h2>User profile loader</h2><ul><li><p><strong>Scenario:</strong> A social media platform needs to display user profiles with real-time data.</p></li><li><p><strong>Implementation:</strong> A loader fetches user data from the database, validates and formats it, and sends it to the frontend for rendering the user profile page.</p></li><li><p><strong>Result:</strong> Users see accurate and up-to-date profile information, improving the overall user experience and satisfaction.</p></li></ul><h1>Benefits of using loaders</h1><h2>Improved performance</h2><p>Loaders enhance performance by fetching and preparing data in advance, reducing the time required to render pages. For example, an ecommerce site using loaders can pre-fetch product data, ensuring that pages load quickly even during high-traffic periods.</p><h2>Enhanced flexibility</h2><p>Loaders provide flexibility by allowing developers to integrate data from multiple sources and transform it as needed. For example, a website can use loaders to fetch and combine data from a CMS, an external API, and a local database, creating a rich and dynamic user experience.</p><h2>Better data management</h2><p>Loaders ensure that data is correctly formatted and validated before being rendered, reducing errors and improving data integrity. For example, a loader can validate user input from a form before storing it in the database, preventing malformed data and ensuring consistency.</p><h1>Challenges in using loaders</h1><h2>Complexity in implementation</h2><p>Implementing loaders can be complex, especially when dealing with multiple data sources and transformation requirements. For example, a developer building a multi-channel content platform must implement loaders to fetch and format data for different devices and screen sizes, which can be challenging.</p><p></p><h2>Performance overhead</h2><p>While loaders improve performance by pre-fetching data, they can also introduce overhead if not optimized properly. For example, a poorly optimized loader that fetches unnecessary data can slow down the application, impacting user experience.</p><p></p><h2>Dependency management</h2><p>Loaders often depend on external APIs and services, which can introduce dependencies that need to be managed carefully. For example, a website relying on an external API for weather data must handle cases where the API is unavailable or returns errors, ensuring that the site remains functional.</p><h1>Loaders and deco</h1><p>Loaders are essential components in CMS and headless CMS environments, responsible for fetching, transforming, and preparing data for rendering. By leveraging loaders, developers can enhance performance, flexibility, and data management in their applications. Deco provides comprehensive support for implementing loaders, ensuring that web applications are dynamic, efficient, and user-friendly.</p><p></p><p>By adopting loaders, businesses can create high-performance web applications that deliver rich and engaging digital experiences. With deco, developers can easily implement loaders to fetch and prepare data from various sources, ensuring that content is delivered efficiently and effectively.</p>"}}