{
  "name": "collections/blog/posts/0d7877e38a29",
  "__resolveType": "blog/loaders/Blogpost.ts",
  "post": {
    "authors": [],
    "categories": [],
    "title": "Customer Success",
    "excerpt": "In a CMS environment, Customer Success focuses on helping users effectively use the platform to meet their content management and website development goals.",
    "date": "2024-08-08",
    "slug": "customer -success",
    "content": "<p>In the competitive landscape of digital products and services, customer success has become a critical factor for achieving long-term business growth and customer retention. Customer Success teams work proactively to ensure that customers derive maximum value from the products or services they use. In the realm of CMS and headless CMS, Customer Success is key in helping users navigate the platform, optimize their content management workflows, and achieve their web development objectives.</p><p></p><h1>What is customer success?</h1><p></p><p>Customer Success is a strategic approach focused on helping customers achieve their desired outcomes while using a product or service. Unlike traditional customer support, which is reactive and addresses specific issues, customer success is proactive and aims to guide customers towards successful and continued use of the product. This involves understanding customer needs, providing personalized guidance, and ensuring they can leverage the product's full potential.</p><p></p><h1>How does customer success work in CMS and headless CMS?</h1><p>In CMS and headless CMS environments, customer success teams are crucial in helping users effectively manage content and develop websites. Here’s how customer success functions within these contexts:</p><p></p><h2>Onboarding and training</h2><p>Customer success teams assist new users in getting started with the CMS or headless CMS platform. This includes providing comprehensive onboarding sessions, training materials, and personalized guidance to ensure users understand how to use the platform effectively. For example, a customer success team might conduct a series of webinars for new users, covering essential topics such as content creation, template customization, and API integration.</p><p></p><h2>Proactive support</h2><p>Rather than waiting for customers to encounter problems, customer success teams proactively reach out to offer support and advice. This can include regular check-ins, performance reviews, and customized recommendations based on the customer's usage patterns. For example, a customer success manager might regularly review a customer's website performance metrics and provide tips on optimizing page load times and improving SEO.</p><p></p><h2>Customer feedback and product improvement</h2><p>Customer success teams gather feedback from users to understand their pain points and areas where the platform can be improved. This feedback is then communicated to the product development team to guide future updates and enhancements. For example, after receiving feedback about difficulties in integrating third-party tools, the team collaborates with the development team to create more seamless integration options.</p><p></p><h1>Examples of customer success in action</h1><p></p><h2>Enhancing user engagement</h2><ul><li><p><strong>Scenario:</strong> A marketing agency uses a headless CMS to manage multiple client websites but struggles with user engagement.</p></li><li><p><strong>Implementation:</strong> The customer success team provides targeted training on advanced features, such as personalized content delivery and A/B testing, to help the agency improve engagement.</p></li><li><p><strong>Result:</strong> The agency successfully implements these features, resulting in higher user engagement and client satisfaction.</p></li></ul><p></p><h2>Optimizing content workflows</h2><ul><li><p><strong>Scenario:</strong> A news organization uses a traditional CMS but faces inefficiencies in its content publishing workflow.</p></li><li><p><strong>Implementation:</strong> The customer success team conducts a workflow analysis and recommends automating certain tasks, such as content scheduling and distribution.</p></li><li><p><strong>Result:</strong> The organization sees a significant reduction in publishing times and an increase in content output, enhancing their overall efficiency.</p></li></ul><p></p><h2>Improving SEO performance</h2><ul><li><p><strong>Scenario:</strong> An ecommerce business using a headless CMS wants to improve its search engine rankings.</p></li><li><p><strong>Implementation:</strong> The customer success team provides a detailed SEO audit and offers actionable insights, such as optimizing meta tags, improving site structure, and enhancing page speed.</p></li><li><p><strong>Result:</strong> The business experiences a boost in organic traffic and better search engine rankings, leading to increased sales.</p></li></ul><p></p><h1>What are the benefits of customer success in CMS and headless CMS? </h1><p></p><h2>Increased customer satisfaction</h2><p>By proactively addressing customer needs and ensuring they can fully utilize the platform, customer success leads to higher customer satisfaction and loyalty.</p><p></p><h2>Enhanced platform adoption</h2><p>Effective customer success strategies help users understand and adopt new features, driving higher usage rates and maximizing the platform's value.</p><p></p><h2>Reduced churn rates</h2><p>Proactive engagement and support reduce the likelihood of customers abandoning the platform, leading to lower churn rates and more stable revenue streams.</p><p></p><h2>Continuous improvement</h2><p>Feedback gathered by customer success teams provides valuable insights for product development, leading to continuous improvements and innovations.</p><p></p><h2>Better ROI for customers</h2><p>Customers who receive proactive support and guidance are more likely to achieve their goals, resulting in a better return on investment (ROI) for the platform.</p><p></p><h1>What are the challenges of implementing customer success?</h1><h2>Resource allocation</h2><p>Implementing an effective customer success strategy requires dedicated resources, including skilled personnel and technology, which can be challenging for smaller organizations.</p><p></p><h2>Balancing proactive and reactive support</h2><p>While proactive support is essential, it's also important to balance it with reactive support to address immediate customer issues efficiently.</p><p></p><h2>Measuring success</h2><p>Quantifying the impact of customer success initiatives can be difficult, as it involves tracking various metrics, such as customer satisfaction, retention rates, and usage patterns.</p><p></p><h1>Customer success and deco</h1><p>Customer Success is a vital aspect of modern CMS and headless CMS platforms, focusing on helping users achieve their desired outcomes and maximizing the value of the product. By providing proactive support, personalized guidance, and continuous engagement, customer success teams ensure higher customer satisfaction, increased platform adoption, and reduced churn rates.</p><p></p><p>Deco places a strong emphasis on customer success to ensure users can fully leverage the platform's capabilities. By providing onboarding, proactive support, continuous engagement, and a community, deco helps users achieve their content management and web development goals. By adopting a customer-centric approach, developers and content managers can ensure their projects are successful and deliver the best possible user experience.</p><p></p>"
  }
}