{
  "name": "collections/blog/posts/eaa85e2b2e18",
  "__resolveType": "blog/loaders/Blogpost.ts",
  "post": {
    "authors": [],
    "categories": [],
    "title": "Omnichannel",
    "excerpt": "Omnichannel is the strategic marketing practice of integrating customer experience across multiple channels.",
    "date": "2024-07-22",
    "slug": "omnichannel",
    "content": "<p>Omnichannel refers to a seamless and integrated approach to content delivery across multiple channels, providing a consistent user experience. In CMS and headless CMS environments, omnichannel strategies ensure that content is unified and accessible whether users interact via websites, mobile apps, social media, or other platforms.</p><p></p><h1>What is omnichannel?</h1><p></p><p>Omnichannel is a strategic approach that provides users with a unified and cohesive experience across all digital and physical channels. Unlike multichannel, which involves only using multiple channels, omnichannel focuses on integrating these channels to ensure a seamless user journey. This means that a user can start an interaction on one channel and continue it on another without any disruption.</p><p></p><h1>How does omnichannel work in CMS and headless CMS?</h1><p></p><p>In both traditional CMS and headless CMS environments, omnichannel strategies are crucial for delivering a unified user experience. Here’s how omnichannel content delivery functions within these contexts:</p><p></p><p><strong>1. Integrated content management:</strong></p><p>Traditional CMS manages content centrally but requires significant customization to deliver an omnichannel experience while headless CMS naturally supports omnichannel strategies by decoupling the content management from the presentation layer, allowing content to be delivered seamlessly to any channel via APIs.</p><p></p><p><strong>2. Seamless user experience:</strong></p><p>Content is synchronized and accessible across all channels, ensuring that users have a consistent experience regardless of how they interact with the brand. For example, a user might start reading an article on a website, continue reading it on a mobile app, and finish it on a smart TV—all without losing their place or experiencing any disruption.</p><p></p><p><strong>3. Real-time synchronization:</strong></p><p>Omnichannel strategies involve real-time data synchronization across channels. This ensures that updates made in one channel are immediately reflected across all others. For example, if a product price is updated in the CMS, the new price is instantly reflected on the website, mobile app, and in-store displays.</p><p></p><h1>Examples of omnichannel in action:</h1><p><strong>Retail industry:</strong></p><ul><li><p><strong>Website:</strong> Customers can browse products, read reviews, and make purchases.</p></li><li><p><strong>Mobile app:</strong> Provides personalized recommendations, order tracking, and mobile-exclusive offers.</p></li><li><p><strong>Physical store:</strong> In-store tablets or kiosks allow customers to check product availability, place orders, and access their online account.</p></li><li><p><strong>Social media:</strong> Shoppable posts and ads direct users to the e-commerce site or app.</p></li><li><p><strong>Customer support:</strong> Chatbots and live support provide assistance across all platforms, maintaining the conversation context</p><p></p></li></ul><p><strong>Banking and finance:</strong></p><ul><li><p><strong>Online banking:</strong> Users can manage accounts, transfer funds, and pay bills through the website.</p></li><li><p><strong>Mobile banking app:</strong> Offers features like mobile deposits, budgeting tools, and real-time notifications.</p></li><li><p><strong>ATMs:</strong> Allow users to withdraw cash, check balances, and perform other banking operations.</p></li><li><p><strong>Customer service:</strong> Support via phone, chat, and email, ensuring all interactions are logged and accessible across channels.</p></li></ul><h1>What are the benefits of using an omnichannel strategy?</h1><ul><li><p><strong>Enhanced user experience:</strong> Provides a consistent and seamless experience across all touchpoints, improving customer satisfaction and loyalty.</p></li><li><p><strong>Increased engagement:</strong> Users are more likely to engage with a brand that offers a unified experience, leading to higher retention and conversion rates.</p></li><li><p><strong>Better data insights: </strong>Real-time data synchronization across channels provides comprehensive insights into user behavior and preferences.</p></li><li><p><strong>Improved efficiency:</strong> Streamlined operations and consistent content delivery reduce redundancy and improve overall efficiency.</p><p></p></li></ul><p>Omnichannel strategies are essential for delivering a unified and seamless user experience across multiple channels. In CMS and headless CMS environments, these strategies ensure that content is consistent, synchronized, and accessible, enhancing user engagement and satisfaction.</p><p></p><p>Deco excels in providing the infrastructure needed to implement effective omnichannel strategies. By leveraging its headless CMS capabilities, deco ensures that content can be managed centrally and delivered seamlessly across all channels. This allows developers to create integrated and cohesive user experiences, whether users interact via websites, mobile apps, social media, or other digital platforms.</p><p></p>",
    "seo": {
      "title": "What is omnichannel?",
      "description": "Omnichannel is the strategic marketing practice of integrating customer experience across multiple channels."
    }
  }
}