{"name":"Blog post EN","path":"/en/blog/:path","sections":{"variants":[{"rule":{"__resolveType":"website/matchers/never.ts"},"value":[{"post":{"page":{"__resolveType":"site/functions/LoadPageProps.ts"},"postList":{"__resolveType":"blogposts"},"__resolveType":"site/loaders/blogPostDetailsLoader.ts"},"locale":"en","__resolveType":"site/sections/BlogPostSEO.tsx","titleTemplate":"deco.cx - %s "},{"__resolveType":"GTM"},{"__resolveType":"Deco Header [EN]"},{"__resolveType":"site/sections/BlogPostHeader.tsx","page":{"__resolveType":"site/functions/LoadPageProps.ts"},"postList":{"__resolveType":"blogposts"},"backToBlog":"Back to blog"},{"__resolveType":"site/sections/Markdown.tsx","post":{"list":{"__resolveType":"blogposts"},"slug":{"param":"path","__resolveType":"deco-sites/std/functions/requestToParam.ts"},"__resolveType":"site/loaders/blogPostMarkdownLoader.ts"},"text":"test"},{"__resolveType":"site/sections/Carousel.tsx","cards":{"page":{"__resolveType":"site/functions/LoadPageProps.ts"},"postList":{"__resolveType":"blogposts"},"__resolveType":"site/loaders/featuredPosts.ts"},"locale":"en","bottomPadding":"96px"},{"__resolveType":"Deco Footer [EN]"}]},{"rule":{"__resolveType":"website/matchers/always.ts"},"value":[{"post":{"page":{"__resolveType":"site/functions/LoadPageProps.ts"},"postList":{"__resolveType":"blogposts"},"__resolveType":"site/loaders/blogPostDetailsLoader.ts"},"locale":"en","__resolveType":"site/sections/BlogPostSEO.tsx","titleTemplate":"deco.cx - %s "},{"__resolveType":"GTM"},{"page":{"__resolveType":"7946"},"__resolveType":"$live/sections/PageInclude.tsx"},{"page":{"__resolveType":"site/functions/LoadPageProps.ts"},"postList":{"__resolveType":"blogposts"},"backToBlog":"Back to blog","__resolveType":"site/sections/BlogPostHeader.tsx"},{"post":{"list":{"__resolveType":"blogposts"},"slug":{"param":"path","__resolveType":"deco-sites/std/functions/requestToParam.ts"},"__resolveType":"site/loaders/blogPostMarkdownLoader.ts"},"text":"test","__resolveType":"site/sections/Markdown.tsx"},{"cards":{"page":{"__resolveType":"site/functions/LoadPageProps.ts"},"postList":{"__resolveType":"blogposts"},"__resolveType":"site/loaders/featuredPosts.ts"},"locale":"en","__resolveType":"site/sections/Carousel.tsx","bottomPadding":"96px"},{"__resolveType":"[en] Footer"}]}],"__resolveType":"website/flags/multivariate.ts"},"__resolveType":"$live/pages/LivePage.tsx"}